pyanca/IterativeMeansAlign.py
pyanca/KabschAlign.py
pyanca/SD2.py
pyanca/TD2.py
pyanca/TD4.py
pyanca/__init__.py
pyanca-0.1.13.dist-info/METADATA
pyanca-0.1.13.dist-info/RECORD
pyanca-0.1.13.dist-info/WHEEL
pyanca-0.1.13.dist-info/top_level.txt
